README.md
setup.py
c7n_salactus/__init__.py
c7n_salactus/cli.py
c7n_salactus/db.py
c7n_salactus/inventory.py
c7n_salactus/objectacl.py
c7n_salactus/rqworker.py
c7n_salactus/worker.py
c7n_salactus.egg-info/PKG-INFO
c7n_salactus.egg-info/SOURCES.txt
c7n_salactus.egg-info/dependency_links.txt
c7n_salactus.egg-info/entry_points.txt
c7n_salactus.egg-info/requires.txt
c7n_salactus.egg-info/top_level.txt