Metadata-Version: 1.1
Name: c7n-salactus
Version: 0.3.0
Summary: Cloud Custodian - Salactus S3
Home-page: https://github.com/capitalone/cloud-custodian
Author: UNKNOWN
Author-email: UNKNOWN
License: Apache-2.0
Platform: UNKNOWN
Classifier: Topic :: System :: Systems Administration
Classifier: Topic :: System :: Distributed Computing
